Dockerfile
LICENSE
MANIFEST.in
Makefile
README.md
README.rst
VERSION
requirements.txt
run.sh
setup.py
upload_chain.conf
contracts/DIDRegistry.sol
contracts/EthereumDIDRegistry.json
contracts/EthereumDIDRegistry.sol
contracts/myPrivateKey.pem
contracts/myPublicKey.pem
docs/index.rst
golang/Makefile
golang/__init__.py
golang/crypto.go
golang/crypto.h
golang/crypto.so
golang/test.py
tests/test.py
tests/test2.py
tests/test_celery.py
tests/test_crypto.py
tests/test_dids.py
tests/test_rabbitmq.py
tests/test_wechat.py
tests/log/oracle-20190320.log
tests/log/oracle-20190409.log
upload_chain/__init__.py
upload_chain/crypto.py
upload_chain/cusomer.py
upload_chain/dids.py
upload_chain/exceptions.py
upload_chain/listeners.py
upload_chain/logger.py
upload_chain/mail.py
upload_chain/main.py
upload_chain/queues.py
upload_chain/setting.py
upload_chain/tasks.py
upload_chain/utils.py
upload_chain/wechat.py
upload_chain/celery/__init__.py
upload_chain/celery/app.py
upload_chain/celery/seting.py
upload_chain/celery/task.py
upload_chain/database/__init__.py
upload_chain/database/dbs.py
upload_chain/database/modles.py
upload_chain/database/status.py
upload_chain/plugins/__init__.py
upload_chain/plugins/notice.py
upload_chain_eth.egg-info/PKG-INFO
upload_chain_eth.egg-info/SOURCES.txt
upload_chain_eth.egg-info/dependency_links.txt
upload_chain_eth.egg-info/entry_points.txt
upload_chain_eth.egg-info/not-zip-safe
upload_chain_eth.egg-info/requires.txt
upload_chain_eth.egg-info/top_level.txt