Metadata-Version: 1.2
Name: upload-chain-eth
Version: 0.0.25
Summary: 专门用于处理队列的上链操作
Home-page: https://gitlab.hard-chain.cn/cport/upload_chain
Author: yuyongpeng
Author-email: yuyongpeng@hotmail.com
License: MIT License
